{
  "openapi": "3.0.0",
  "info": {
    "title": "TakoHalo",
    "version": "1.0.0",
    "description": ""
  },
  "servers": [
    {
      "url": "https://localhost:5001/api"
    },
    {
      "url": ""
    }
  ],
  "paths": {
    "/auth/signup": {
      "post": {
        "summary": "SignUp",
        "responses": {},
        "requestBody": {
          "content": {
            "application/json": {
              "schema": {
                "type": "object",
                "properties": {
                  "username": {
                    "type": "string"
                  },
                  "password": {
                    "type": "string",
                    "format": "color"
                  },
                  "email": {
                    "type": "string",
                    "format": "email"
                  },
                  "firstName": {
                    "type": "string"
                  },
                  "lastName": {
                    "type": "string"
                  }
                }
              },
              "example": {
                "username": "userTest01",
                "password": "abc",
                "email": "userTest@gmail.com",
                "firstName": "User",
                "lastName": "Tran"
              }
            }
          }
        }
      }
    },
    "/auth/signin": {
      "post": {
        "summary": "SignIn",
        "responses": {},
        "requestBody": {
          "content": {
            "application/json": {
              "schema": {
                "type": "object",
                "properties": {
                  "username": {
                    "type": "string"
                  },
                  "password": {
                    "type": "string",
                    "format": "color"
                  }
                }
              },
              "example": {
                "username": "user1",
                "password": "abc"
              }
            }
          }
        }
      }
    },
    "/auth/signout": {
      "post": {
        "summary": "SignOut",
        "responses": {},
        "security": [
          {
            "BearerAuth": []
          }
        ]
      }
    },
    "/": {
      "get": {
        "summary": "AuthMe",
        "responses": {}
      }
    },
    "/message/direct": {
      "post": {
        "summary": "SendDirectMessage",
        "responses": {},
        "security": [
          {
            "BearerAuth": []
          }
        ],
        "requestBody": {
          "content": {
            "application/json": {
              "schema": {
                "type": "object",
                "properties": {
                  "recipientId": {
                    "type": "string"
                  },
                  "content": {
                    "type": "string"
                  }
                }
              },
              "example": {
                "recipientId": "6a38bbbe4203b308074e288e",
                "content": "usernhien gửi tin nhắn cho user1"
              }
            }
          }
        }
      }
    }
  },
  "components": {
    "securitySchemes": {
      "BearerAuth": {
        "type": "http",
        "scheme": "bearer"
      }
    }
  }
}